{"slug":"bpssc-2026-122","id":"bpssc-2026-122","title":"BPSSC हवलदार इंस्ट्रक्टर भर्ती 2026 – 122 पद – ऑनलाइन फॉर्म","category":"Latest_Notifications","org":"","vacancies":"","lastDate":"","postDate":"2026-05-29","applyMode":"Online","location":"India","shortInfo":"","sourceUrl":"https://sarkarinetwork.com/bpssc-havildar-instructor-recruitment-2026/","education":[],"state":[],"tags":["10th","latest"],"detail":{"name":"BPSSC हवलदार इंस्ट्रक्टर भर्ती 2026 – 122 पद – ऑनलाइन फॉर्म","url":"https://sarkarinetwork.com/bpssc-havildar-instructor-recruitment-2026/"},"name":"BPSSC हवलदार इंस्ट्रक्टर भर्ती 2026 – 122 पद – ऑनलाइन फॉर्म","url":"https://sarkarinetwork.com/bpssc-havildar-instructor-recruitment-2026/"}