{"slug":"cbse-board-12","id":"cbse-board-12","title":"CBSE board कक्षा 12वीं का रिजल्ट जारी डाउनलोड करें","category":"Latest_Notifications","org":"","vacancies":"","lastDate":"","postDate":"2026-05-29","applyMode":"Online","location":"India","shortInfo":"","sourceUrl":"https://cbseresults.nic.in/class_xii_b_2026_a/ClassTwelfth_ii26.htm","education":[],"state":[],"tags":["latest"],"detail":{"name":"CBSE board कक्षा 12वीं का रिजल्ट जारी डाउनलोड करें","url":"https://cbseresults.nic.in/class_xii_b_2026_a/ClassTwelfth_ii26.htm"},"name":"CBSE board कक्षा 12वीं का रिजल्ट जारी डाउनलोड करें","url":"https://cbseresults.nic.in/class_xii_b_2026_a/ClassTwelfth_ii26.htm"}