{"slug":"iiser-2026","id":"iiser-2026","title":"IISER मोहाली नॉन-टीचिंग भर्ती 2026 – टेंडेंट, नर्स, फार्मासिस्ट, ऑफिस असिस्टेंट व अन्य पद","category":"Latest_Notifications","org":"","vacancies":"","lastDate":"","postDate":"2026-05-28","applyMode":"Online","location":"India","shortInfo":"","sourceUrl":"https://sarkariresultshine.com/mohali-iiser-non-teaching-vacancy-2026/","education":[],"state":[],"tags":["latest"],"detail":{"name":"IISER मोहाली नॉन-टीचिंग भर्ती 2026 – टेंडेंट, नर्स, फार्मासिस्ट, ऑफिस असिस्टेंट व अन्य पद","url":"https://sarkariresultshine.com/mohali-iiser-non-teaching-vacancy-2026/"},"name":"IISER मोहाली नॉन-टीचिंग भर्ती 2026 – टेंडेंट, नर्स, फार्मासिस्ट, ऑफिस असिस्टेंट व अन्य पद","url":"https://sarkariresultshine.com/mohali-iiser-non-teaching-vacancy-2026/"}