{"state_id":"delhi","state":"Delhi","name":"AIIMS Delhi – Project Assistant I – 1 Posts","url":"","date":"Last Date: 01-06-2026","lastDate":"01-06-2026","qualification":"B.Sc, Diploma","postDate":"19/05/2026","board":"AIIMS Delhi","detail":{"basic_details":{"job_title":"AIIMS Delhi Project Assistant I Recruitment 2026 - Apply Online","short_information":"All India Institute of Medical Sciences Delhi (AIIMS Delhi) Recruitment 2026 for 1 post of Project Assistant I. Candidates with B.Sc Can Apply Online. The last date to apply online is 01-06-2026. The candidate shall apply online through AIIMS Delhi official website.","post_name":"Total Posts","application_mode":"Email","job_type":"Contract","organization_name":"AIIMS Delhi","post_date":"19/05/2026","advt_no":"–"},"important_dates":{"last_date_to_apply":"01 June 2026","notification_date":"15 May 2026"},"application_fee":{},"age_limit":{"age_details":"Max: 50 years"},"qualification":{"education_qualification":"B.Sc. / 3 years diploma in Engineering & Technology from a recognized university or Equivalent."},"vacancy_details":[],"category_wise_vacancy":{},"salary_details":{"pay_scale":"Rs. 20000 Per Month"},"selection_process":[],"exam_pattern":{},"syllabus":{},"physical_eligibility":{},"how_to_apply":["Candidates who wish to apply for AIIMS Delhi Project Assistant I Recruitment 2026 via email should follow the steps below."],"important_instructions":[],"important_links":{"click_here":["https://www.aiims.edu/images/pdf/recruitment/advertisement/burnsurgery-18-5-26.pdf"],"notification_pdf":"https://www.aiims.edu/images/pdf/recruitment/advertisement/burnsurgery-18-5-26.pdf"},"faq":[],"seo_tags":["All India Institute of Medical Sciences Delhi Project Assistant I Recruitment 2026","AIIMS Delhi Recruitment 2026","AIIMS Delhi Project Assistant I Jobs 2026","AIIMS Delhi Project Assistant I Careers","Latest AIIMS Delhi Jobs","AIIMS Delhi Notification 2026","AIIMS Delhi Vacancy 2026","AIIMS Delhi Online Form 2026","AIIMS Delhi Apply Online","All India Institute of Medical Sciences Delhi Jobs 2026"]}}