{"title":"चंडीगढ़ पुलिस होम गार्ड भर्ती 2026 – 155 पद – शॉर्ट नोटिस जारी","slug":"2026-155","category":"Latest_Notifications","basic_details":{"job_title":"चंडीगढ़ पुलिस होम गार्ड भर्ती 2026 – 155 पद – शॉर्ट नोटिस जारी","post_name":"चंडीगढ़ पुलिस होम गार्ड भर्ती 2026 – 155 पद – शॉर्ट नोटिस जारी","total_vacancies":"","application_mode":"Online","job_location":"India","short_information":"","last_updated":""},"important_dates":{"last_date_to_apply":""},"source_url":"https://sarkariresultshine.com/chandigarh-police-home-guard-recruitment-2026/","section":"Top 20 Jobs"}