{"basic_details":{"job_title":"AIIMS Bilaspur – Research Coordinator – 1 Posts","organization_name":"AIIMS Bilaspur","post_name":"Total Posts","total_vacancies":"","application_mode":"Walk-in","job_location":"Himachal Pradesh, India","short_information":"All India Institute of Medical Sciences, Bilaspur (AIIMS Bilaspur) Recruitment 2026 for 1 Research Coordinator post. Candidates with B.Sc. (MLT) or B.Sc. Nursing qualification can attend the walk-in interview on 09-06-2026 through the official AIIMS Bilaspur website, aiimsbilaspur.edu.in.","last_updated":"28/05/2026"},"important_dates":{"last_date_to_apply":"03 June 2026","notification_date":"01 May 2026"},"application_fee":{},"age_limit":{"age_details":"Max: 30 years"},"qualification":{"education_qualification":"B.Sc. (MLT), B.Sc. Nursing"},"vacancy_details":[],"category_wise_vacancy":{},"salary_details":{"pay_scale":"Rs. 25000 Per Month"},"selection_process":[],"exam_pattern":{},"syllabus":{},"physical_eligibility":{},"how_to_apply":[],"important_instructions":[],"important_links":{"click_here":["https://www.aiimsbilaspur.edu.in/common/images/recruitment/z0jqnvy5Advertisment%20Nephrology.pdf","http://www.aiimsbilaspur.edu.in/common/images/recruitment/z0jqnvy5Advertisment%20Nephrology.pdf","https://www.aiimsbilaspur.edu.in/common/images/recruitment/ppgq6zi2%28Annexure-1%29%20Application%20Form.pdf"],"notification_pdf":"https://www.aiimsbilaspur.edu.in/common/images/recruitment/z0jqnvy5Advertisment%20Nephrology.pdf"},"faq":[],"seo_tags":["AIIMS Bilaspur Research Coordinator Recruitment 2026 - Walkin"],"category":"Latest_Notifications","slug":"aiims-bilaspur-research-coordinator-1-posts","state":"Himachal Pradesh","source_url":""}