{"title":"BHU – Research Associate, Project Assistant, Sanskrit Consultant – 3 Posts","slug":"bhu-research-associate-project-assistant-sanskrit-consultant-3-posts","category":"Latest_Notifications","basic_details":{"job_title":"BHU Recruitment 2026 - Apply Offline for Research Associate, Project Assistant and More Posts","short_information":"Banaras Hindu University (BHU) Recruitment 2026 for 3 posts of Research Associate, Project Assistant, Sanskrit Consultant. Candidates with Ph.D, Postgraduate Can Apply Offline. The last date to apply offline is 2026-05-25. The candidate shall apply offline through BHU official website.","post_name":"Salary","application_mode":"Offline","job_type":"Contractual","organization_name":"BHU","post_date":"21/05/2026","advt_no":"–"},"important_dates":{"last_date_to_apply":"25 May 2026","notification_date":"02 May 2026"},"source_url":"https://www.bhu.ac.in/Site/TempVacancyDetail/1_2_16?2061","state":"Uttar Pradesh","application_fee":{},"age_limit":{"age_details":"10-06-2026"},"qualification":{"education_qualification":"Ph.D. in Ancient Indian History, Culture & Archaeology / Sanskrit / Ancient History / Indology or allied subject, Postgraduate in relevant subject with UGC-NET/JRF and research experience in Purāṇic studies, Postgraduate in Ancient Indian History, Culture & Archaeology / Sanskrit / Ancient History / Archaeology / Indology with minimum 55% marks, Acharya/M.A. in Sanskrit with proficiency in Purāṇic Sanskrit texts, translation and manuscript reading"},"vacancy_details":[],"category_wise_vacancy":{},"salary_details":{"pay_scale":"Rs. 8000 - 30000 Per Month"},"selection_process":[],"exam_pattern":{},"syllabus":{},"physical_eligibility":{},"how_to_apply":["Candidates who wish to apply for BHU Various Posts Recruitment 2026 through offline mode should follow the steps below."],"important_instructions":[],"important_links":{"click_here":["https://www.bhu.ac.in/Site/TempVacancyDetail/1_2_16?2061","https://www.bhu.ac.in"]},"faq":[],"seo_tags":["Banaras Hindu University Research Associate","Project Assistant & More Recruitment 2026","BHU Recruitment 2026","BHU Research Associate","Project Assistant & More Jobs 2026","BHU Research Associate","Project Assistant & More Careers","Latest BHU Jobs","BHU Notification 2026","BHU Vacancy 2026","BHU Offline Form 2026","BHU Apply Offline","Banaras Hindu University Jobs 2026"]}