{"basic_details":{"job_title":"CISF – ASI Paramedical Staff – 24 Posts","organization_name":"CISF","post_name":"Minimum Age","total_vacancies":"","application_mode":"Online","job_location":"Delhi, India","short_information":"The Central Industrial Security Force (CISF) will recruit 24 ASI Para Medical Staff posts, which will be filled through CISF Recruitment 2026. Interested candidates can apply online from 08 June 2026 to 07 July 2026. Check details like eligibility, salary, apply online, vacancy, exam pattern & more from the article.","last_updated":"02/06/2026"},"important_dates":{"start_date":"08 June 2026","last_date_to_apply":"09 July 2026 (upto 2359 Hrs)"},"application_fee":{},"age_limit":{"age_details":"07 July 2026"},"qualification":{"education_qualification":"Diploma, D.Pharm, DMLT"},"vacancy_details":[],"category_wise_vacancy":{},"salary_details":{"pay_scale":"Pay Level-5, 7th CPC (Rs. 29,200 – 92,300/-)"},"selection_process":["Written Exam (OMR/CBT) – PST – Documentation – BVAT – Medical Examination"],"exam_pattern":{},"syllabus":{},"physical_eligibility":{},"how_to_apply":["Here, we have provided the direct, simple and easy steps to apply online for the CISF ASI Para Medical Staff Recruitment 2026. Every candidate can follow these steps one by one and submit the application form."],"important_instructions":[],"important_links":{},"faq":[],"seo_tags":["CISF ASI Para Medical Staff Recruitment 2026 Notification Out For 24 Posts, Apply Online Starts 08 June 2026"],"category":"Latest_Notifications","slug":"cisf-asi-paramedical-staff-24-posts","state":"Delhi","source_url":""}