{"slug":"dlsa-sitapur-stenographer-recruitment-2026-apply-offline","title":"DLSA Sitapur Stenographer Recruitment 2026 - Apply Offline","source":"freejobalert","category":"Latest_Notifications","organization":"District Legal Services Authority Sitapur (DLSA Sitapur)","department":"","post_name":"Stenographer","total_vacancies":"1","notification_number":"","application_mode":"Offline","job_type":"Contractual","job_category":"","job_location":"Pan India","official_website":"","short_info":"District Legal Services Authority Sitapur (DLSA Sitapur) Stenographer Notification 2026 has been released on 29 May 2026 on the official website. A total of 1 vacancy has been announced through the DLSA Sitapur Stenographer Recruitment 2026.","last_updated":"01 Jun 2026","selection_process_brief":"","last_date":"30-06-2026","notification_date":"29 May 2026","important_dates":{"last_date_to_apply":"30-06-2026","event":"Date","notification date":"29 May 2026"},"application_fee":{},"age_limit":{"age_details":"Max: 65 years","details":"Maximum Age Limit: 65 years."},"qualification":{"education_qualification":"Retired as Stenographer from District Court or Collectorate Court","details":"Retired as Stenographer from District Court or Collectorate Court."},"vacancy_details":[{"Post Name":"Stenographer","Total Posts":"1"},{"Post Name":"Total","Total Posts":"1"}],"category_wise_vacancy":{"Post Name":"Total","Total Posts":"1"},"salary_details":{"pay_scale":"Rs. 9000 Per Month","details":"Rs. 9000 Per Month"},"selection_process":["Application Scrutiny Document Verification"],"exam_pattern":{},"syllabus":{},"physical_eligibility":{},"how_to_apply":["Read the official notification carefully before applying.","Download the application form from the official website: .","Fill the application form carefully with correct information.","Attach self-attested copies of required documents such as photograph, signature, ID proof, and certificates."],"important_instructions":[],"faq":[],"seo_tags":[],"important_links":{"click_here":["http://cdnbbsr.s3waas.gov.in/s3ec0515e122e839dfdaa7ce969536f94a/uploads/2026/05/2026052955.pdf","https://sitapur.dcourts.gov.in/"],"notification_pdf":"https://cdnbbsr.s3waas.gov.in/s3ec0515e122e839dfdaa7ce969536f94a/uploads/2026/05/2026052955.pdf"},"all_links":[],"useful_links":[],"tables":null,"sections":[],"text_sections":[],"jobs_info":"","salary_pay_scale":"","minimum_age":"","maximum_age":"","status":"active","post_date":"","categories":[],"all_qualifications":[],"is_latest":true,"is_reminder":false}