{"title":"ICAR CIRB Hisar Vacancy 2026 केंद्रीय भैंस अनुसंधान संस्थान, हिसार में निकली 'यंग प्रोफेशनल' के पदों पर भर्ती Last Date: 14/05/2026","slug":"icar-cirb-hisar-vacancy-2026-last-date-14052026","category":"Latest_Notifications","basic_details":{"job_title":"ICAR CIRB Hisar Vacancy 2026 केंद्रीय भैंस अनुसंधान संस्थान, हिसार में निकली 'यंग प्रोफेशनल' के पदों पर भर्ती Last Date: 14/05/2026","post_name":"ICAR CIRB Hisar Vacancy 2026 केंद्रीय भैंस अनुसंधान संस्थान, हिसार में निकली 'यंग प्रोफेशनल' के पदों पर भर्ती Last Date: 14/05/2026","total_vacancies":"","application_mode":"Online","job_location":"India","short_information":"","last_updated":""},"important_dates":{"last_date_to_apply":""},"source_url":"https://sarkariresultshine.com/icar-cirb-hisar-vacancy-2026-apply-now/"}