{"slug":"icmr-scientist-d-recruitment-2026-apply-online","title":"ICMR Scientist-D Recruitment 2026 - Apply Online","source":"freejobalert","category":"MBBS","organization":"Indian Council of Medical Research (ICMR)","department":"","post_name":"Scientist D","total_vacancies":"2","notification_number":"","application_mode":"Online","job_type":"Full Time","job_category":"","job_location":"","official_website":"","short_info":"Indian Council of Medical Research (ICMR) Scientist D Notification 2026 has been released on 27 May 2026 on the official website of ICMR. A total of 2 vacancies have been announced through the ICMR Scientist D Recruitment 2026.","last_updated":"29 May 2026","selection_process_brief":"","last_date":"29-06-2026","notification_date":"27 May 2026","important_dates":{"last_date_to_apply":"29-06-2026","event":"Date","notification date":"27 May 2026"},"application_fee":{"general_fee":"Rs.1500/-","sc_fee":"Nil","female_fee":"Nil"},"age_limit":{"age_details":"Max: 45 years","details":"Maximum Age Limit: 45 years. Age relaxation is relaxable in accordance with GOI instructions."},"qualification":{"education_qualification":"MBBS or equivalent degree recognised by MCI/NMC with 8 Years experience","details":"MBBS or equivalent degree recognised by MCI/NMC with 8 Years experience. Desirable: MD/MS or equivalent degree recognised by MCI/NMC or MPH from a recognised university or Ph.D. from a recognised University in a subject related to Biomedical sciences.","matched_qualifications":["MBBS","MS_MD","MPhil_PhD"]},"vacancy_details":[{"Post Name":"Scientist D","Total Posts":"2"},{"Post Name":"Total","Total Posts":"2"}],"category_wise_vacancy":{"Post Name":"Total","Total Posts":"2"},"salary_details":{"pay_scale":"Rs. 78800 - 209200 Per Month","details":"Salary: Rs. 78800 - 209200 Per Month (Level 12 of Pay Matrix)"},"selection_process":["Computer-based test (MCQs) Interview"],"exam_pattern":{},"syllabus":{},"physical_eligibility":{},"how_to_apply":["Candidates who meet the eligibility criteria can apply online for the ICMR Scientist D Recruitment 2026.","Applications must be submitted online on or before 29-06-2026.","To apply directly, use the Apply Online link provided in the Important Links section.","Alternatively, candidates may visit the official website of ICMR to complete the application."],"important_instructions":[],"faq":[],"seo_tags":[],"important_links":{"click_here":["https://recruitment.icmr.org.in/","https://www.icmr.gov.in/"],"notification_pdf":"https://www.icmr.gov.in/icmrobject/uploads/Recruitment/1780045884_scientist-dmedicalclinicaltrialsadvt.pdf"},"all_links":[],"useful_links":[],"tables":null,"sections":[],"text_sections":[],"jobs_info":"","salary_pay_scale":"","minimum_age":"","maximum_age":"","status":"active","post_date":"","categories":["MBBS","MS_MD","MPhil_PhD"],"all_qualifications":["MBBS","MS_MD","MPhil_PhD"],"is_latest":false,"is_reminder":false}