{"basic_details":{"job_title":"IIT Delhi Junior Research Fellow Recruitment 2026 - Walkin","last_updated":"11 May 2026","organization_name":"Indian Institute of Technology Delhi","post_name":"Junior Research Fellow","total_vacancies":"1","application_mode":"Walk-in","job_type":"Contract","short_information":"Indian Institute of Technology Delhi (IIT Delhi) Jr. Research Fellow Notification 2026 has been released on the official website of Indian Institute of Technology Delhi. A total of 1 vacancy has been announced through the IIT Delhi Jr. Research Fellow Recruitment 2026. Candidates who have completed 1st class B.Tech in Civil Engineering and 1st class M.Tech in Geotechnical Engineering along with NET/GATE qualification are eligible to apply for these Jr. Research Fellow vacancies. The walk-in interview for IIT Delhi Jr. Research Fellow Recruitment 2026 is scheduled to be held on 10 June 2026. Ca","job_location":"Delhi"},"important_dates":{"event":"Date","interview_date":"10 June 2026"},"application_fee":{},"age_limit":{},"qualification":{"education_qualification":"B.Tech in Civil Engineering, 1st class M.Tech","details":"1st class B.Tech in Civil Engineering and 1st class M.Tech in Geotechnical Engineering. Experience in conducting laboratory and model-scale experiments, specifically focusing on the application of acoustic emissions in geotechnical engineering for early prediction of failures. NET/GATE qualified. The requirement of NET/GATE examination may be relaxed for candidates graduated from Centrally Funded Technical Institutes (CFTIs) with CGPA more than 8.000 (80% aggregate marks).","matched_qualifications":["B_Tech_BE","M_E_MTech","CA"]},"vacancy_details":[{"Post Name":"Junior Research Fellow","Total Posts":"1"},{"Post Name":"Total","Total Posts":"1"}],"category_wise_vacancy":{"Post Name":"Total","Total Posts":"1"},"salary_details":{"pay_scale":"Rs. 37,000 Per Month","details":"Rs. 37,000 Per Month"},"selection_process":["Walk-in test Interview"],"exam_pattern":{},"syllabus":{},"physical_eligibility":{},"how_to_apply":[],"important_instructions":[],"important_links":{"click_here":["https://ird.iitd.ac.in/api/uploadsProjectPositions/project_position_1777965781726_pifwxsp.pdf","http://ird.iitd.ac.in"],"notification_pdf":"https://ird.iitd.ac.in/api/uploadsProjectPositions/project_position_1777965781726_pifwxsp.pdf"},"category":"B_Tech_BE"}