{"basic_details":{"job_title":"RSLSA – Panel Advocate","organization_name":"RSLSA","post_name":"Total Posts","total_vacancies":"","application_mode":"Offline","job_location":"Rajasthan, India","short_information":"Rajasthan State Legal Services Authority (RSLSA) Recruitment 2026 for posts of Panel Advocate. Candidates Can Apply Offline. The last date to apply offline is 15-06-2026. The candidate shall apply offline through RSLSA official website.","last_updated":"28/05/2026"},"important_dates":{"last_date_to_apply":"15 June 2026","notification_date":"24 May 2026"},"application_fee":{},"age_limit":{},"qualification":{"education_qualification":"Advocate enrolled with Bar Council with more than 1 year regular practice experience as per Advocates Act 1961"},"vacancy_details":[],"category_wise_vacancy":{},"salary_details":{},"selection_process":[],"exam_pattern":{},"syllabus":{},"physical_eligibility":{},"how_to_apply":["Candidates who wish to apply for RSLSA Various Posts Recruitment 2026 through offline mode should follow the steps below."],"important_instructions":[],"important_links":{"click_here":["https://cdnbbsr.s3waas.gov.in/s3ec02a64bd53139f71961c5c31a9af03d/uploads/2026/05/2026052743.pdf","https://pali.dcourts.gov.in/"],"notification_pdf":"https://cdnbbsr.s3waas.gov.in/s3ec02a64bd53139f71961c5c31a9af03d/uploads/2026/05/2026052743.pdf"},"faq":[],"seo_tags":["RSLSA Panel Advocate Recruitment 2026 - Apply Offline"],"category":"Latest_Notifications","slug":"pali.dcourts.gov.in","state":"Rajasthan","source_url":"https://pali.dcourts.gov.in/"}