{"basic_details":{"job_title":"UP Anganwadi Recruitment 2026 - Apply Online for 210 Anganwadi Workers and Helper Posts in Chandauli District","last_updated":"08 Jul 2026","total_vacancies":"Anganwadi Karyakatri (Worker) and Anganwadi Sahayika (Helper)","post_name":"Honorarium-based","application_mode":"Online only","official_website":"upanganwadibharti.in","short_information":"UP Anganwadi Recruitment 2026 has been announced by the Office of the District Programme Officer, Child Development, Chandauli through an official notification (Vigyapti) dated 04 July 2026. This recruitment drive invites online applications from eligible female candidates for the honorarium-based posts of Anganwadi Karyakatri (Worker) and Anganwadi Sahayika (Helper) across the rural and urban areas of Chandauli district, Uttar Pradesh. A total of 84 Karyakatri posts and 126 Sahayika posts are vacant across 10 child development projects in the district. Interested and eligible candidates can a","job_location":"Chandauli, Uttar Pradesh"},"important_dates":{"last_date_to_apply":"25 July 2026, 12:00 midnight","raw":"Notification Released: 04 July 2026 Age Cut-off Date: 01 July 2026 Online Application Start Date: As per departmental website upanganwadibharti.in Last Date to Apply Online: 25 July 2026 (till 12:00 midnight) Offline Applications: Not accepted under any circumstances"},"application_fee":{"details":"The official notification does not mention any application fee for the Anganwadi Karyakatri and Sahayika recruitment 2026. Candidates should check the online application portal, upanganwadibharti.in, at the time of filling the form for confirmed and updated fee details, if any."},"age_limit":{"details":"Minimum Age: 18 years Maximum Age: 35 years Age Cut-off Date: 01 July 2026 No age relaxation is applicable to any caste category."},"qualification":{"details":"Only female candidates are eligible to apply for these posts. The candidate must be a permanent resident of the Gram Sabha/Ward (urban area) where the vacant post exists. The Gram Sabha includes all revenue villages, majra, purva, and tolas that fall under it. If an eligible candidate belonging to the notified category is not available within the Gram Sabha, an eligible candidate from the concerned Nyay Panchayat will be selected instead."},"vacancy_details":[{"S.No.":"1","Project":"Sakaldiha","Unreserved (UR)":"11","OBC":"5","SC":"3","ST":"2","Total":"21"},{"S.No.":"2","Project":"Chakia","Unreserved (UR)":"9","OBC":"5","SC":"3","ST":"0","Total":"17"},{"S.No.":"3","Project":"Naugarh","Unreserved (UR)":"3","OBC":"1","SC":"1","ST":"0","Total":"5"},{"S.No.":"4","Project":"Aware","Unreserved (UR)":"1","OBC":"1","SC":"1","ST":"0","Total":"3"},{"S.No.":"5","Project":"Barhani","Unreserved (UR)":"3","OBC":"2","SC":"1","ST":"0","Total":"6"},{"S.No.":"6","Project":"Shahabganj","Unreserved (UR)":"1","OBC":"0","SC":"1","ST":"0","Total":"2"},{"S.No.":"7","Project":"Chahaniya","Unreserved (UR)":"4","OBC":"2","SC":"1","ST":"0","Total":"7"},{"S.No.":"8","Project":"Dhanapur","Unreserved (UR)":"4","OBC":"3","SC":"3","ST":"0","Total":"10"},{"S.No.":"9","Project":"Niyamatabad","Unreserved (UR)":"5","OBC":"1","SC":"4","ST":"0","Total":"10"},{"S.No.":"10","Project":"Nagar","Unreserved (UR)":"2","OBC":"0","SC":"1","ST":"0","Total":"3"},{"S.No.":"Total","Project":"","Unreserved (UR)":"43","OBC":"20","SC":"19","ST":"2","Total":"84"},{"S.No.":"1","Project":"Sakaldiha","Unreserved (UR)":"16","OBC":"11","SC":"5","ST":"0","Total":"32"},{"S.No.":"2","Project":"Chakia","Unreserved (UR)":"8","OBC":"5","SC":"6","ST":"1","Total":"20"},{"S.No.":"3","Project":"Naugarh","Unreserved (UR)":"3","OBC":"0","SC":"3","ST":"0","Total":"6"},{"S.No.":"4","Project":"Aware","Unreserved (UR)":"3","OBC":"2","SC":"0","ST":"0","Total":"5"},{"S.No.":"5","Project":"Barhani","Unreserved (UR)":"11","OBC":"7","SC":"7","ST":"0","Total":"25"},{"S.No.":"6","Project":"Shahabganj","Unreserved (UR)":"1","OBC":"0","SC":"0","ST":"0","Total":"1"},{"S.No.":"7","Project":"Chahaniya","Unreserved (UR)":"2","OBC":"2","SC":"1","ST":"0","Total":"5"},{"S.No.":"8","Project":"Dhanapur","Unreserved (UR)":"10","OBC":"3","SC":"3","ST":"0","Total":"16"},{"S.No.":"9","Project":"Niyamatabad","Unreserved (UR)":"10","OBC":"2","SC":"0","ST":"0","Total":"12"},{"S.No.":"10","Project":"Nagar","Unreserved (UR)":"2","OBC":"1","SC":"1","ST":"0","Total":"4"},{"S.No.":"Total","Project":"","Unreserved (UR)":"66","OBC":"33","SC":"26","ST":"1","Total":"126"}],"vacancy_breakdown":{"category_wise_breakdown":[{"s_no":1,"project":"Sakaldiha","unreserved_ur":11,"obc":5,"sc":3,"st":2,"total":21},{"s_no":2,"project":"Chakia","unreserved_ur":9,"obc":5,"sc":3,"st":0,"total":17},{"s_no":3,"project":"Naugarh","unreserved_ur":3,"obc":1,"sc":1,"st":0,"total":5},{"s_no":4,"project":"Aware","unreserved_ur":1,"obc":1,"sc":1,"st":0,"total":3},{"s_no":5,"project":"Barhani","unreserved_ur":3,"obc":2,"sc":1,"st":0,"total":6},{"s_no":6,"project":"Shahabganj","unreserved_ur":1,"obc":0,"sc":1,"st":0,"total":2},{"s_no":7,"project":"Chahaniya","unreserved_ur":4,"obc":2,"sc":1,"st":0,"total":7},{"s_no":8,"project":"Dhanapur","unreserved_ur":4,"obc":3,"sc":3,"st":0,"total":10},{"s_no":9,"project":"Niyamatabad","unreserved_ur":5,"obc":1,"sc":4,"st":0,"total":10},{"s_no":10,"project":"Nagar","unreserved_ur":2,"obc":0,"sc":1,"st":0,"total":3},{"s_no":"Total","project":"","unreserved_ur":43,"obc":20,"sc":19,"st":2,"total":84},{"s_no":1,"project":"Sakaldiha","unreserved_ur":16,"obc":11,"sc":5,"st":0,"total":32},{"s_no":2,"project":"Chakia","unreserved_ur":8,"obc":5,"sc":6,"st":1,"total":20},{"s_no":3,"project":"Naugarh","unreserved_ur":3,"obc":0,"sc":3,"st":0,"total":6},{"s_no":4,"project":"Aware","unreserved_ur":3,"obc":2,"sc":0,"st":0,"total":5},{"s_no":5,"project":"Barhani","unreserved_ur":11,"obc":7,"sc":7,"st":0,"total":25},{"s_no":6,"project":"Shahabganj","unreserved_ur":1,"obc":0,"sc":0,"st":0,"total":1},{"s_no":7,"project":"Chahaniya","unreserved_ur":2,"obc":2,"sc":1,"st":0,"total":5},{"s_no":8,"project":"Dhanapur","unreserved_ur":10,"obc":3,"sc":3,"st":0,"total":16},{"s_no":9,"project":"Niyamatabad","unreserved_ur":10,"obc":2,"sc":0,"st":0,"total":12},{"s_no":10,"project":"Nagar","unreserved_ur":2,"obc":1,"sc":1,"st":0,"total":4},{"s_no":"Total","project":"","unreserved_ur":66,"obc":33,"sc":26,"st":1,"total":126}]},"category_wise_vacancy":{"Unreserved (UR)":"66","OBC":"33","SC":"26","ST":"1"},"salary_details":{"details":"The posts of Anganwadi Karyakatri and Sahayika are honorarium-based (मानदेय आधारित) appointments and not regular salaried government jobs. The official notification does not specify the exact honorarium amount. Candidates are advised to refer to the detailed vacancy notice displayed at the CDPO office, Vikas Bhawan, or the official website upanganwadibharti.in, or the government order dated 17 September 2025 for the applicable honorarium structure."},"selection_process":["Selection to the posts of Anganwadi Karyakatri and Sahayika will be made on the basis of a merit list prepared as per the criteria mentioned in the Government Order No. /2025/3313/58-1-2025 (1917687) dated 17 September 2025","considering:","Educational qualification (up to postgraduate level","for merit purposes) Residency of the applicant in the relevant Gram Sabha/Ward Reservation category (UR/OBC/SC/ST) Priority rules for BPL widow","BPL divorced/abandoned woman","BPL and APL candidates as applicable"],"exam_pattern":{},"syllabus":{},"physical_eligibility":{},"how_to_apply":["Visit the official departmental website: upanganwadibharti.in","Locate the notification for Chandauli Anganwadi Karyakatri/Sahayika Recruitment 2026-27.","Register using your basic details and create login credentials.","Fill in the online application form carefully with personal, educational, and residential details.","Upload the scanned copies of all required documents and photograph as specified.","Review the filled application form thoroughly to avoid errors.","Submit the application form before the last date, i.e., 25 July 2026, midnight 12:00.","Save or print the confirmation/acknowledgment for future reference."],"important_instructions":["Selection for the posts of Anganwadi Karyakatri and Sahayika will follow a defined order of preference among eligible resident candidates of the same Gram Sabha/Ward:","Widow women living Below Poverty Line (BPL) will be given first priority. A valid death certificate issued by the Gram Panchayat Officer/concerned urban body and an attested copy of the family register will be required. If a BPL widow is not available, preference will go to a BPL divorced/abandoned (Parityakta) woman. A valid legal order from the competent court is required in such cases. If candidates from both the above categories are not available, preference will be given to a BPL candidate, followed by an APL (Above Poverty Line) candidate.","Only income certificates issued by a competent authority (Tehsildar), as per UP Government Order No. 3959/1-9-11-Raj-9 dated 30 September 2011, that are online-verifiable will be accepted. As per the redefined poverty line income limits (Government Order dated 14 September 2015), the annual income limit is Rs. 46,080 for rural areas and Rs. 56,460 for urban areas. BPL/Antyodaya ration cards will not be accepted as proof of poverty status.","Only applications submitted online through upanganwadibharti.in within the prescribed period will be accepted. Offline applications will not be accepted or considered. Two candidates/women from the same family will not be selected at one Anganwadi center. Applications containing errors or incomplete information will not be considered. For more information regarding the recruitment process, candidates may contact the District Programme Officer office (near Vikas Bhawan, G.T. Road, Bichhiyakala, Chandauli) or the respective Block Child Development Project Officer (CDPO) office on working days. Detailed project-wise, Gram Panchayat-wise, and ward-wise vacancy and reservation details are displayed on notice boards at the Collectorate, Vikas Bhawan, Tehsil, Development Block, CDPO office, and DPO office."],"important_links":{"click_here":["https://upanganwadibharti.in/workernew/uploadOrder/ordercopy_1783344875_71947ae1.pdf","http://upanganwadibharti.in"],"_labels":{"click_here":"Official Notification","notification_pdf":"Download UP Anganwadi Workers and Helper Job 2026 Notification PDF"},"notification_pdf":"https://upanganwadibharti.in/workernew/uploadOrder/ordercopy_1783344875_71947ae1.pdf"},"all_official_links":[{"label":"Download UP Anganwadi Workers and Helper Job 2026 Notification PDF","url":"https://upanganwadibharti.in/workernew/uploadOrder/ordercopy_1783344875_71947ae1.pdf"}],"content_sections":[{"heading":"UP Anganwadi Recruitment 2026: Overview","text":"","tables":[{"caption":"","rows":[{"particulars":"Organisation","details":"Office of the District Programme Officer, Child Development, Chandauli (Bal Vikas Chandauli)"},{"particulars":"Notification Name","details":"Anganwadi Karyakatri & Sahayika Recruitment Notification 2026-27"},{"particulars":"Notification Date","details":"04 July 2026"},{"particulars":"Posts","details":"Anganwadi Karyakatri (Worker) and Anganwadi Sahayika (Helper)"},{"particulars":"Total Vacancies","details":"210 (84 Karyakatri + 126 Sahayika)"},{"particulars":"Nature of Post","details":"Honorarium-based"},{"particulars":"Eligible Candidates","details":"Female candidates only"},{"particulars":"Application Mode","details":"Online only"},{"particulars":"Official Website","details":"upanganwadibharti.in"},{"particulars":"Last Date to Apply","details":"25 July 2026, 12:00 midnight"}]}]},{"heading":"UP Anganwadi Recruitment 2026 Important Dates","text":"Notification Released: 04 July 2026 Age Cut-off Date: 01 July 2026 Online Application Start Date: As per departmental website upanganwadibharti.in Last Date to Apply Online: 25 July 2026 (till 12:00 midnight) Offline Applications: Not accepted under any circumstances","tables":[]},{"heading":"Chandauli Anganwadi Vacancy Details 2026 (Project-wise)","text":"The recruitment notification mentions that this vacancy arose after 16 Anganwadi Sahayikas were promoted to the post of Anganwadi Karyakatri, following approval by the District Magistrate dated 02 July 2026, as per Government Order No. /2025/3313/58-1-2025 (1917687) dated 17 September 2025. The department has clarified that the number of vacancies shown below may increase, decrease, or change based on the departmental status at the time of final selection. Note: The complete project-wise, Gram Panchayat-wise and ward-wise vacancy details along with full reservation and eligibility information have been displayed on the notice boards of the District Collectorate, Vikas Bhawan, Tehsil, Development Block, Child Development Project Officer offices and the District Programme Officer office of Chandauli, and are also uploaded on upanganwadibharti.in.","tables":[{"caption":"1. Anganwadi Karyakatri (Worker) Post - Vacancy Table","rows":[{"s_no":1,"project":"Sakaldiha","unreserved_ur":11,"obc":5,"sc":3,"st":2,"total":21},{"s_no":2,"project":"Chakia","unreserved_ur":9,"obc":5,"sc":3,"st":0,"total":17},{"s_no":3,"project":"Naugarh","unreserved_ur":3,"obc":1,"sc":1,"st":0,"total":5},{"s_no":4,"project":"Aware","unreserved_ur":1,"obc":1,"sc":1,"st":0,"total":3},{"s_no":5,"project":"Barhani","unreserved_ur":3,"obc":2,"sc":1,"st":0,"total":6},{"s_no":6,"project":"Shahabganj","unreserved_ur":1,"obc":0,"sc":1,"st":0,"total":2},{"s_no":7,"project":"Chahaniya","unreserved_ur":4,"obc":2,"sc":1,"st":0,"total":7},{"s_no":8,"project":"Dhanapur","unreserved_ur":4,"obc":3,"sc":3,"st":0,"total":10},{"s_no":9,"project":"Niyamatabad","unreserved_ur":5,"obc":1,"sc":4,"st":0,"total":10},{"s_no":10,"project":"Nagar","unreserved_ur":2,"obc":0,"sc":1,"st":0,"total":3},{"s_no":"Total","project":"","unreserved_ur":43,"obc":20,"sc":19,"st":2,"total":84}]},{"caption":"2. Anganwadi Sahayika (Helper) Post - Vacancy Table","rows":[{"s_no":1,"project":"Sakaldiha","unreserved_ur":16,"obc":11,"sc":5,"st":0,"total":32},{"s_no":2,"project":"Chakia","unreserved_ur":8,"obc":5,"sc":6,"st":1,"total":20},{"s_no":3,"project":"Naugarh","unreserved_ur":3,"obc":0,"sc":3,"st":0,"total":6},{"s_no":4,"project":"Aware","unreserved_ur":3,"obc":2,"sc":0,"st":0,"total":5},{"s_no":5,"project":"Barhani","unreserved_ur":11,"obc":7,"sc":7,"st":0,"total":25},{"s_no":6,"project":"Shahabganj","unreserved_ur":1,"obc":0,"sc":0,"st":0,"total":1},{"s_no":7,"project":"Chahaniya","unreserved_ur":2,"obc":2,"sc":1,"st":0,"total":5},{"s_no":8,"project":"Dhanapur","unreserved_ur":10,"obc":3,"sc":3,"st":0,"total":16},{"s_no":9,"project":"Niyamatabad","unreserved_ur":10,"obc":2,"sc":0,"st":0,"total":12},{"s_no":10,"project":"Nagar","unreserved_ur":2,"obc":1,"sc":1,"st":0,"total":4},{"s_no":"Total","project":"","unreserved_ur":66,"obc":33,"sc":26,"st":1,"total":126}]}]},{"heading":"Chandauli Anganwadi Bharti 2026 Eligibility Criteria","text":"Only female candidates are eligible to apply for these posts. The candidate must be a permanent resident of the Gram Sabha/Ward (urban area) where the vacant post exists. The Gram Sabha includes all revenue villages, majra, purva, and tolas that fall under it. If an eligible candidate belonging to the notified category is not available within the Gram Sabha, an eligible candidate from the concerned Nyay Panchayat will be selected instead.","tables":[]},{"heading":"Salary / Honorarium for Anganwadi Karyakatri and Sahayika","text":"The posts of Anganwadi Karyakatri and Sahayika are honorarium-based (मानदेय आधारित) appointments and not regular salaried government jobs. The official notification does not specify the exact honorarium amount. Candidates are advised to refer to the detailed vacancy notice displayed at the CDPO office, Vikas Bhawan, or the official website upanganwadibharti.in, or the government order dated 17 September 2025 for the applicable honorarium structure.","tables":[]},{"heading":"Application Fee","text":"The official notification does not mention any application fee for the Anganwadi Karyakatri and Sahayika recruitment 2026. Candidates should check the online application portal, upanganwadibharti.in, at the time of filling the form for confirmed and updated fee details, if any.","tables":[]},{"heading":"Preference / Priority Rules in Selection","text":"Selection for the posts of Anganwadi Karyakatri and Sahayika will follow a defined order of preference among eligible resident candidates of the same Gram Sabha/Ward: Widow women living Below Poverty Line (BPL) will be given first priority. A valid death certificate issued by the Gram Panchayat Officer/concerned urban body and an attested copy of the family register will be required. If a BPL widow is not available, preference will go to a BPL divorced/abandoned (Parityakta) woman. A valid legal order from the competent court is required in such cases. If candidates from both the above categories are not available, preference will be given to a BPL candidate, followed by an APL (Above Poverty Line) candidate. Only income certificates issued by a competent authority (Tehsildar), as per UP Government Order No. 3959/1-9-11-Raj-9 dated 30 September 2011, that are online-verifiable will be accepted. As per the redefined poverty line income limits (Government Order dated 14 September 2015), the annual income limit is Rs. 46,080 for rural areas and Rs. 56,460 for urban areas. BPL/Antyodaya ration cards will not be accepted as proof of poverty status.","tables":[]},{"heading":"Selection Process","text":"Selection to the posts of Anganwadi Karyakatri and Sahayika will be made on the basis of a merit list prepared as per the criteria mentioned in the Government Order No. /2025/3313/58-1-2025 (1917687) dated 17 September 2025, considering: Educational qualification (up to postgraduate level, for merit purposes) Residency of the applicant in the relevant Gram Sabha/Ward Reservation category (UR/OBC/SC/ST) Priority rules for BPL widow, BPL divorced/abandoned woman, BPL and APL candidates as applicable","tables":[]},{"heading":"Required Documents","text":"Educational qualification certificates and mark sheets Residence certificate (issued online with digital signature from Tehsil) Caste certificate (issued online with digital signature from Tehsil, where applicable) Income certificate issued by Tehsildar (online-verifiable) Death certificate of husband and family register copy (for widow candidates) Court order/legal document (for divorced/abandoned candidates) Recent passport-size photograph Valid mobile number and email ID for registration","tables":[]},{"heading":"How to Apply Online for UP Anganwadi Recruitment 2026","text":"Visit the official departmental website: upanganwadibharti.in Locate the notification for Chandauli Anganwadi Karyakatri/Sahayika Recruitment 2026-27. Register using your basic details and create login credentials. Fill in the online application form carefully with personal, educational, and residential details. Upload the scanned copies of all required documents and photograph as specified. Review the filled application form thoroughly to avoid errors. Submit the application form before the last date, i.e., 25 July 2026, midnight 12:00. Save or print the confirmation/acknowledgment for future reference.","tables":[]},{"heading":"Important Instructions for Candidates","text":"Only applications submitted online through upanganwadibharti.in within the prescribed period will be accepted. Offline applications will not be accepted or considered. Two candidates/women from the same family will not be selected at one Anganwadi center. Applications containing errors or incomplete information will not be considered. For more information regarding the recruitment process, candidates may contact the District Programme Officer office (near Vikas Bhawan, G.T. Road, Bichhiyakala, Chandauli) or the respective Block Child Development Project Officer (CDPO) office on working days. Detailed project-wise, Gram Panchayat-wise, and ward-wise vacancy and reservation details are displayed on notice boards at the Collectorate, Vikas Bhawan, Tehsil, Development Block, CDPO office, and DPO office.","tables":[{"caption":"","rows":[{"district_wise_anganwadi_vacancies":"128 Anganwadi Worker & Helper Posts in Shravasti","direct_link":"Click Here"},{"district_wise_anganwadi_vacancies":"75 Posts in Lalitpur District","direct_link":"Click Here"},{"district_wise_anganwadi_vacancies":"787 Anganwadi Worker & Helper Posts in Bijnour, Kanpur District","direct_link":"Click Here"},{"district_wise_anganwadi_vacancies":"760 Anganwadi Worker & Helper Posts in Bagpat, Kannauj District","direct_link":"Click Here"},{"district_wise_anganwadi_vacancies":"180 Anganwadi Worker Posts in Meerut District","direct_link":"Click Here"},{"district_wise_anganwadi_vacancies":"187 Anganwadi Worker Posts in Varanasi District","direct_link":"Click Here"},{"district_wise_anganwadi_vacancies":"236 Anganwadi Worker Posts in Mathura District","direct_link":"Click Here"},{"district_wise_anganwadi_vacancies":"292 Anganwadi Worker Posts in Farrukhabad District","direct_link":"Click Here"},{"district_wise_anganwadi_vacancies":"250 Anganwadi Worker Posts in Pratapgarh District","direct_link":"Click Here"},{"district_wise_anganwadi_vacancies":"708 Anganwadi Worker Posts in Agra District","direct_link":"Click Here"}]}]},{"heading":"Important Links","text":"","tables":[{"caption":"","rows":[{"link":"Official Notification","url":"Click Here"},{"link":"Online Application Portal","url":"Click Here"},{"link":"Official Website","url":"Click Here"}]}]}],"faq":[{"question":"Q1. What is UP Anganwadi Recruitment 2026 for Chandauli?","answer":"It is an official recruitment drive by the District Programme Officer, Child Development, Chandauli to fill 84 Anganwadi Karyakatri and 126 Anganwadi Sahayika honorarium-based posts across 10 projects in the district."},{"question":"Q2. Who can apply for Chandauli Anganwadi Bharti 2026?","answer":"Only female candidates who are permanent residents of the concerned Gram Sabha or Ward, aged between 18 and 35 years as on 01 July 2026, with a minimum qualification of Intermediate, can apply."},{"question":"Q3. What is the last date to apply for Anganwadi Karyakatri/Sahayika posts in Chandauli?","answer":"The last date to submit the online application is 25 July 2026, till midnight 12:00."},{"question":"Q4. What is the total number of vacancies?","answer":"There are 84 vacancies for Anganwadi Karyakatri and 126 vacancies for Anganwadi Sahayika, totaling 210 posts, though the department has clarified that these numbers may change."},{"question":"Q5. Is there any application fee for this recruitment?","answer":"The official notification does not mention any application fee. Candidates should check the application portal for confirmation."},{"question":"Q6. Where can I apply for UP Anganwadi Recruitment 2026?","answer":"Applications can be submitted only online through the official website upanganwadibharti.in. Offline applications are not accepted."},{"question":"Q7. Is age relaxation available for reserved categories?","answer":"No, the notification clearly states that no age relaxation is applicable to any caste category."},{"question":"What is UP Anganwadi Recruitment 2026 for Chandauli?","answer":"It is an official recruitment drive by the District Programme Officer, Child Development, Chandauli to fill 84 Anganwadi Karyakatri and 126 Anganwadi Sahayika honorarium-based posts across 10 projects in the district."},{"question":"Who can apply for Chandauli Anganwadi Bharti 2026?","answer":"Only female candidates who are permanent residents of the concerned Gram Sabha or Ward, aged between 18 and 35 years as on 01 July 2026, with a minimum qualification of Intermediate, can apply."},{"question":"What is the last date to apply for Anganwadi Karyakatri/Sahayika posts in Chandauli?","answer":"The last date to submit the online application is 25 July 2026, till midnight 12:00."},{"question":"What is the total number of vacancies?","answer":"There are 84 vacancies for Anganwadi Karyakatri and 126 vacancies for Anganwadi Sahayika, totaling 210 posts, though the department has clarified that these numbers may change."},{"question":"Is there any application fee for this recruitment?","answer":"The official notification does not mention any application fee. Candidates should check the application portal for confirmation."},{"question":"Where can I apply for UP Anganwadi Recruitment 2026?","answer":"Applications can be submitted only online through the official website upanganwadibharti.in. Offline applications are not accepted."},{"question":"Is age relaxation available for reserved categories?","answer":"No, the notification clearly states that no age relaxation is applicable to any caste category."}],"_scraped_from":"https://www.freejobalert.com/articles/up-anganwadi-recruitment-2026-apply-online-for-210-anganwadi-workers-and-helper-posts-in-chandauli-district-3057266","slug":"up-anganwadi-recruitment-2026-apply-online-for-210-anganwadi-workers-and-helpe","category":"Latest_Notifications"}