{"title":"WAMUL – Assistant – 1 Posts","slug":"wamul-assistant-1-posts","category":"Latest_Notifications","basic_details":{"job_title":"WAMUL Assistant Recruitment 2026 - Apply Online","short_information":"West Assam Milk Producers' Co-operative Union (WAMUL) Recruitment 2026 for 1 post of Assistant – Warehouse & Logistics. Candidates with Graduation Can Apply Online. The online application opens on 23-05-2026, and closes on 11-06-2026. The candidate shall apply online through WAMUL official website.","post_name":"Total Posts","application_mode":"Online","job_type":"Contract","organization_name":"WAMUL","post_date":"26/05/2026","advt_no":"WAMUL/2026-27/05"},"important_dates":{"last_date_to_apply":"11 June 2026","start_date":"23 May 2026"},"source_url":"","state":"Assam","application_fee":{},"age_limit":{"age_details":"Not above 28 years as on 1st January, 2026."},"qualification":{"education_qualification":"Full time Graduation from a recognized Institute/University."},"vacancy_details":[],"category_wise_vacancy":{},"salary_details":{"pay_scale":"Rs. 4.55 lakhs per annum"},"selection_process":[],"exam_pattern":{},"syllabus":{},"physical_eligibility":{},"how_to_apply":["Candidates who meet the eligibility criteria can apply online for the WAMUL Assistant – Warehouse & Logistics Recruitment 2026."],"important_instructions":[],"important_links":{"click_here":["https://recruitment.purabi.coop/files/REOI_23_05_2026.pdf","https://recruitment.purabi.coop/files/TOR%20Assistant%20Warehouse%20&%20Logistics.pdf"],"notification_pdf":"https://recruitment.purabi.coop/files/REOI_23_05_2026.pdf"},"faq":[],"seo_tags":["West Assam Milk Producers' Co-operative Union Assistant – Warehouse & Logistics Recruitment 2026","WAMUL Recruitment 2026","WAMUL Assistant – Warehouse & Logistics Jobs 2026","WAMUL Assistant – Warehouse & Logistics Careers","Latest WAMUL Jobs","WAMUL Notification 2026","WAMUL Vacancy 2026","WAMUL Online Form 2026","WAMUL Apply Online","West Assam Milk Producers' Co-operative Union Jobs 2026"]}